twblog_reader/__init__.py
twblog_reader/__main__.py
twblog_reader/entities.py
twblog_reader/feed.py
twblog_reader/ui.py
twblog-0.1.0.dist-info/LICENSE
twblog-0.1.0.dist-info/METADATA
twblog-0.1.0.dist-info/WHEEL
twblog-0.1.0.dist-info/entry_points.txt
twblog-0.1.0.dist-info/top_level.txt
twblog-0.1.0.dist-info/RECORD
